{
    "ulifyi": "Ulifyi",
    "login_title": "Anmelden",
    "login_notice": "Sie haben noch kein Konto? Registrieren",
    "login": "Anmelden",
    "register_title": "Registrieren",
    "register_notice": "Sie haben bereits ein Konto? Anmelden",
    "register": "Registrieren",
    "name": "Name",
    "username": "Benutzername",
    "email": "E-Mail",
    "password": "Passwort",
    "confirm_password": "Passwort bestätigen",
    "remember_me": "Angemeldet bleiben",
    "forgot_password": "Passwort vergessen?",
    "reset_password": "Passwort zurücksetzen",
    "send_password_reset_link": "Link zum Zurücksetzen des Passworts senden",
    "logout": "Abmelden",
    "verify_email": "E-Mail-Adresse verifizieren",
    "verify_email_notice": "Eine neue Verifizierungs-E-Mail wurde an Ihre E-Mail-Adresse gesendet.",
    "verify_email_notice2": "Bevor Sie fortfahren, überprüfen Sie bitte Ihre E-Mails auf einen Link zur Verifizierung Ihrer E-Mail-Adresse.",
    "verify_email_notice3": "Wenn Sie keine E-Mail erhalten haben,",
    "verify_email_notice4": "klicken Sie hier, um eine weitere anzufordern",
    "verify_email_notice5": "Wenn Sie die E-Mail nicht erhalten haben, überprüfen Sie bitte auch Ihren Spam-Ordner.",
    "verify_email_notice6": "Wenn Sie die E-Mail immer noch nicht erhalten haben,",
    "verify_email_notice7": "klicken Sie hier, um uns zu kontaktieren",
    "error": "Ein fehler ist aufgetreten!",
    "error_404": "Seite nicht gefunden!",
    "fill_all_fields": "Bitte füllen Sie alle Felder aus!",
    "success": "Erfolg!",
    "success_register": "Sie haben sich erfolgreich registriert!",
    "success_verify": "Sie haben Ihre E-Mail-Adresse erfolgreich verifiziert!",
    "success_reset": "Sie haben Ihr Passwort erfolgreich zurückgesetzt!",
    "success_logout": "Sie haben sich erfolgreich abgemeldet!",
    "success_login": "Sie haben sich erfolgreich angemeldet!",
    "success_update": "Sie haben Ihr Profil erfolgreich aktualisiert!",
    "dashboard": "Dashboard",
    "home": "Home",
    "profile": "Profil",
    "your_profile": "Ihr Profil",
    "update_profile": "Profil aktualisieren",
    "connections": "Verbindungen",
    "your_connections": "Ihre Verbindungen",
    "add_connection": "Verbindung hinzufügen",
    "edit_connection": "Verbindung bearbeiten",
    "delete_connection": "Verbindung löschen",
    "settings": "Einstellungen",
    "admin": "Admin"
}